{
	"info": {
		"_postman_id": "1b05f6e0-3d13-46b4-8dd1-2576a62d991a",
		"name": "Auth-postman",
		"schema": "https://schema.getpostman.com/json/collection/v2.1.0/collection.json",
		"_exporter_id": "37775038"
	},
	"item": [
		{
			"name": "login",
			"request": {
				"method": "POST",
				"header": [],
				"body": {
					"mode": "raw",
					"raw": "{\r\n  \r\n    \"email\":\"hassan@gmail.com\",\r\n    \"password\":\"12345\"\r\n}",
					"options": {
						"raw": {
							"language": "json"
						}
					}
				},
				"url": {
					"raw": "localhost:8080/login",
					"host": [
						"localhost"
					],
					"port": "8080",
					"path": [
						"login"
					]
				}
			},
			"response": []
		},
		{
			"name": "register",
			"request": {
				"method": "POST",
				"header": [],
				"body": {
					"mode": "raw",
					"raw": "{\r\n   \" username\":\"mostafa\",\r\n    \"email\":\"mostafa@gmail.com\",\r\n    \"password\":\"mostafa12345#\",\r\n    \"role\":\"SuperAdmin\"\r\n}",
					"options": {
						"raw": {
							"language": "json"
						}
					}
				},
				"url": {
					"raw": "http://localhost:8080/register",
					"protocol": "http",
					"host": [
						"localhost"
					],
					"port": "8080",
					"path": [
						"register"
					]
				}
			},
			"response": []
		},
		{
			"name": "create",
			"request": {
				"method": "POST",
				"header": [
					{
						"key": "Authorization",
						"value": "eyJhbGciOiJIUzI1NiIsInR5cCI6IkpXVCJ9.eyJpZCI6IjY2YzhjYmUxNGU2YTg2MjhjNmQzMjkwNiIsImVtYWlsIjoiaGFzc2FuQGdtYWlsLmNvbSIsInJvbGUiOiJTdXBlckFkbWluIiwidXNlcm5hbWUiOiJoYXNzYW4iLCJpYXQiOjE3MjUxMzIxMDIsImV4cCI6MTcyNTEzNTcwMn0.Qmo2ZriG3_dUs8vRF17dkp6eLx1I0zvWk32DYEOWH8k",
						"type": "text"
					}
				],
				"body": {
					"mode": "raw",
					"raw": "{\r\n    \"title\":\"tv\",\r\n    \"price\":9000,\r\n    \"quantity\":26\r\n}",
					"options": {
						"raw": {
							"language": "json"
						}
					}
				},
				"url": {
					"raw": "localhost:8080",
					"host": [
						"localhost"
					],
					"port": "8080"
				}
			},
			"response": []
		},
		{
			"name": "update",
			"request": {
				"method": "PUT",
				"header": [
					{
						"key": "Authorization",
						"value": "eyJhbGciOiJIUzI1NiIsInR5cCI6IkpXVCJ9.eyJpZCI6IjY2YzhjYmUxNGU2YTg2MjhjNmQzMjkwNiIsImVtYWlsIjoiaGFzc2FuQGdtYWlsLmNvbSIsInJvbGUiOiJTdXBlckFkbWluIiwidXNlcm5hbWUiOiJoYXNzYW4iLCJpYXQiOjE3MjUxMzIxMDIsImV4cCI6MTcyNTEzNTcwMn0.Qmo2ZriG3_dUs8vRF17dkp6eLx1I0zvWk32DYEOWH8k",
						"type": "text"
					}
				],
				"body": {
					"mode": "raw",
					"raw": "{\r\n    \"price\":4500,\r\n    \"quantity\":25\r\n}",
					"options": {
						"raw": {
							"language": "json"
						}
					}
				},
				"url": {
					"raw": "localhost:8080/66d36e1b7c36e707c90cf0cd",
					"host": [
						"localhost"
					],
					"port": "8080",
					"path": [
						"66d36e1b7c36e707c90cf0cd"
					]
				}
			},
			"response": []
		},
		{
			"name": "read",
			"request": {
				"method": "GET",
				"header": [
					{
						"key": "Authorization",
						"value": "eyJhbGciOiJIUzI1NiIsInR5cCI6IkpXVCJ9.eyJpZCI6IjY2YzhjYmUxNGU2YTg2MjhjNmQzMjkwNiIsImVtYWlsIjoiaGFzc2FuQGdtYWlsLmNvbSIsInJvbGUiOiJTdXBlckFkbWluIiwidXNlcm5hbWUiOiJoYXNzYW4iLCJpYXQiOjE3MjUxMzIxMDIsImV4cCI6MTcyNTEzNTcwMn0.Qmo2ZriG3_dUs8vRF17dkp6eLx1I0zvWk32DYEOWH8k",
						"type": "text"
					}
				],
				"url": {
					"raw": "localhost:8080",
					"host": [
						"localhost"
					],
					"port": "8080"
				}
			},
			"response": []
		},
		{
			"name": "delete",
			"request": {
				"method": "DELETE",
				"header": [
					{
						"key": "Authorization",
						"value": "eyJhbGciOiJIUzI1NiIsInR5cCI6IkpXVCJ9.eyJpZCI6IjY2YzhjYmUxNGU2YTg2MjhjNmQzMjkwNiIsImVtYWlsIjoiaGFzc2FuQGdtYWlsLmNvbSIsInJvbGUiOiJTdXBlckFkbWluIiwidXNlcm5hbWUiOiJoYXNzYW4iLCJpYXQiOjE3MjUxMzIxMDIsImV4cCI6MTcyNTEzNTcwMn0.Qmo2ZriG3_dUs8vRF17dkp6eLx1I0zvWk32DYEOWH8k",
						"type": "text"
					}
				],
				"url": {
					"raw": "localhost:8080/66d20eca2a29de4a3773e304",
					"host": [
						"localhost"
					],
					"port": "8080",
					"path": [
						"66d20eca2a29de4a3773e304"
					]
				}
			},
			"response": []
		},
		{
			"name": "read single product",
			"request": {
				"method": "GET",
				"header": [
					{
						"key": "Authorization",
						"value": "eyJhbGciOiJIUzI1NiIsInR5cCI6IkpXVCJ9.eyJpZCI6IjY2YzhjYmUxNGU2YTg2MjhjNmQzMjkwNiIsImVtYWlsIjoiaGFzc2FuQGdtYWlsLmNvbSIsInJvbGUiOiJTdXBlckFkbWluIiwidXNlcm5hbWUiOiJoYXNzYW4iLCJpYXQiOjE3MjUxMzIxMDIsImV4cCI6MTcyNTEzNTcwMn0.Qmo2ZriG3_dUs8vRF17dkp6eLx1I0zvWk32DYEOWH8k",
						"type": "text"
					}
				],
				"url": {
					"raw": "localhost:8080/66d20fef2a29de4a3773e312",
					"host": [
						"localhost"
					],
					"port": "8080",
					"path": [
						"66d20fef2a29de4a3773e312"
					]
				}
			},
			"response": []
		}
	]
}